safesort.py
safesort-0.2.0.dist-info/DESCRIPTION.rst
safesort-0.2.0.dist-info/METADATA
safesort-0.2.0.dist-info/metadata.json
safesort-0.2.0.dist-info/RECORD
safesort-0.2.0.dist-info/top_level.txt
safesort-0.2.0.dist-info/WHEEL
