Metadata-Version: 2.0
Name: safesort
Version: 0.2.0
Summary: Safely sort heterogeneous collections.
Home-page: https://github.com/wolever/safesort
Author: David Wolever
Author-email: david@wolever.net
License: BSD
Platform: UNKNOWN
Classifier: Development Status :: 3 - Alpha
Classifier: Intended Audience :: Developers
Classifier: License :: OSI Approved :: BSD License
Classifier: Natural Language :: English
Classifier: Operating System :: OS Independent
Classifier: Programming Language :: Python
Classifier: Programming Language :: Python :: 2
Classifier: Programming Language :: Python :: 3
Classifier: Topic :: Software Development
